jointbox_opi_zero/__init__.py
jointbox_opi_zero/drivers.py
jointbox_opi_zero/version.py
jointbox_opi_zero-0.2.0.dist-info/DESCRIPTION.rst
jointbox_opi_zero-0.2.0.dist-info/METADATA
jointbox_opi_zero-0.2.0.dist-info/RECORD
jointbox_opi_zero-0.2.0.dist-info/WHEEL
jointbox_opi_zero-0.2.0.dist-info/metadata.json
jointbox_opi_zero-0.2.0.dist-info/top_level.txt
