Metadata-Version: 2.0
Name: jointbox-opi-zero
Version: 0.2.0
Summary: Orange PI Zero specific drivers for jointbox
Home-page: http://jointbox.org
Author: Dmitry Berezovsky
Author-email: UNKNOWN
License: GPLv3
Keywords: home automation smarthouse arduino gpio sensors hardware temperature relay
Platform: UNKNOWN
Classifier: Development Status :: 3 - Alpha
Classifier: Intended Audience :: Developers
Classifier: Topic :: Software Development :: Build Tools
Classifier: License :: OSI Approved :: GNU General Public License v3 (GPLv3)
Classifier: Programming Language :: Python :: 3
Classifier: Programming Language :: Python :: 3.4
Classifier: Programming Language :: Python :: 3.5
Classifier: Programming Language :: Python :: 3.6
Requires-Dist: jointbox (>=0.1.1)
Requires-Dist: pyA20 (==0.2.12)
Provides-Extra: dev
Provides-Extra: test
